[{"Boundaries": [[5309, 5325]], "Type": "Person", "Entity": "pope gregori xii"},{"Boundaries": [[5831, 5840]], "Type": "Person", "Entity": "bessarion"},{"Boundaries": [[6458, 6473]], "Type": "Person", "Entity": "scipion rebiba"},{"Boundaries": [[5682, 5689], [5759, 5766]], "Type": "Person", "Entity": "gregori"},{"Boundaries": [[5856, 5869]], "Type": "Person", "Entity": "pietro riario"},{"Boundaries": [[6761, 6789]], "Type": "Person", "Entity": "francesco maria macchiavelli"},{"Boundaries": [[4681, 4687]], "Type": "Person", "Entity": "pietro"},{"Boundaries": [[5773, 5788]], "Type": "Person", "Entity": "isidor of kiev"},{"Boundaries": [[7858, 7892]], "Type": "Person", "Entity": "alessandro sanminiatelli zabarella"},{"Boundaries": [[6620, 6653]], "Type": "Person", "Entity": "bonifazio bevilacqua aldobrandini"},{"Boundaries": [[7191, 7196], [7471, 7476]], "Type": "Person", "Entity": "maria"},{"Boundaries": [[5803, 5821]], "Type": "Person", "Entity": "basilio bessarion"},{"Boundaries": [[3364, 3378]], "Type": "Person", "Entity": "pope clement v"},{"Boundaries": [[6372, 6377]], "Type": "Person", "Entity": "fabio"},{"Boundaries": [[7536, 7555]], "Type": "Person", "Entity": "fabio maria asquini"},{"Boundaries": [[7042, 7047]], "Type": "Person", "Entity": "luigi"},{"Boundaries": [[7683, 7717]], "Type": "Person", "Entity": "ruggero luigi emidio antici mattei"},{"Boundaries": [[7907, 7920]], "Type": "Person", "Entity": "carlo nocella"},{"Boundaries": [[5648, 5667]], "Type": "Person", "Entity": "francesco condulm"},{"Boundaries": [[746, 750], [1552, 1556], [1638, 1642], [2009, 2014], [2139, 2143], [2149, 2153], [2325, 2329], [2428, 2432], [3812, 3817], [4662, 4666]], "Type": "Person", "Entity": "pope"},{"Boundaries": [[6312, 6326]], "Type": "Person", "Entity": "marino grimani"},{"Boundaries": [[6194, 6210]], "Type": "Person", "Entity": "gile of viterbo"},{"Boundaries": [[5430, 5439], [6261, 6270], [7306, 7315]], "Type": "Person", "Entity": "francesco"},{"Boundaries": [[6562, 6576]], "Type": "Person", "Entity": "silvio savelli"},{"Boundaries": [[6523, 6529]], "Type": "Person", "Entity": "rebiba"},{}]