[{"Boundaries": [[4793, 4810]], "Type": "Person\r", "Entity": "william j . wilgu"}, {"Boundaries": [[580, 598]], "Type": "Person\r", "Entity": "william blackston"}, {"Boundaries": [[479, 488]], "Type": "Person\r", "Entity": "accursiu"}, {"Boundaries": [[1189, 1220]], "Type": "Organisation\r", "Entity": "feder aviat administr"}, {"Boundaries": [[5464, 5501]], "Type": "Organisation\r", "Entity": "metropolitan transport author"}, {"Boundaries": [[5538, 5551]], "Type": "Organisation\r", "Entity": "new york jet"}, {"Boundaries": [[6014, 6033]], "Type": "PopulatedPlace\r", "Entity": "citi of lo angel"}, {"Boundaries": [[4772, 4785], [5436, 5449]], "Type": "PopulatedPlace\r", "Entity": "new york citi"}, {"Boundaries": [[1149, 1162], [1170, 1183], [2038, 2051], [3512, 3525]], "Type": "PopulatedPlace\r", "Entity": "unit state"}, {"Boundaries": [[5961, 5967]], "Type": "PopulatedPlace\r", "Entity": "boston"}, {"Boundaries": [[6132, 6141]], "Type": "PopulatedPlace\r", "Entity": "hollywood"}]