[{"Boundaries": [[0, 4]], "Type": "Person", "Entity": "john"},{"Boundaries": [[1599, 1610]], "Type": "Person", "Entity": "leon green"},{"Boundaries": [[587, 598]], "Type": "Person", "Entity": "hitchcock"},{"Boundaries": [[4177, 4196]], "Type": "Person", "Entity": "hirsti daili dose"},{"Boundaries": [[11, 18]], "Type": "Person", "Entity": "patrick"},{"Boundaries": [[2669, 2686]], "Type": "Person", "Entity": "robert d . cardona"},{"Boundaries": [[1251, 1262]], "Type": "Person", "Entity": "roger moor"},{"Boundaries": [[19, 24], [121, 126], [558, 563], [888, 893], [1324, 1329], [1450, 1457], [2569, 2574], [3652, 3659], [3690, 3697], [4250, 4255]], "Type": "Person", "Entity": "allen"},{}]