[{"Boundaries": [[4392, 4398]], "Type": "Person", "Entity": "murphi"},{"Boundaries": [[2657, 2670], [7790, 7803]], "Type": "Person", "Entity": "lloyd bentsen"},{"Boundaries": [[2115, 2128], [4875, 4888]], "Type": "Person", "Entity": "lawton chile"},{"Boundaries": [[5229, 5234]], "Type": "Person", "Entity": "smith"},{"Boundaries": [[2290, 2306], [4690, 4706]], "Type": "Person", "Entity": "john j . william"},{"Boundaries": [[5223, 5228]], "Type": "Person", "Entity": "tyler"},{"Boundaries": [[2066, 2082], [4824, 4840]], "Type": "Person", "Entity": "spessard holland"},{"Boundaries": [[3020, 3036], [6993, 7009]], "Type": "Person", "Entity": "jame l . buckley"},{"Boundaries": [[115, 130]], "Type": "Person", "Entity": "richard nixon"},{"Boundaries": [[5376, 5389], [5412, 5425]], "Type": "Person", "Entity": "edmund muski"},{"Boundaries": [[5748, 5759], [5782, 5793]], "Type": "Person", "Entity": "philip hart"},{"Boundaries": [[6736, 6737], [7444, 7445]], "Type": "Person", "Entity": "g ."},{"Boundaries": [[7073, 7080]], "Type": "Person", "Entity": "goodel"},{"Boundaries": [[5340, 5349]], "Type": "Person", "Entity": "roudebush"},{"Boundaries": [[2748, 2762], [4352, 4366]], "Type": "Person", "Entity": "john v . tunney"},{"Boundaries": [[307, 320], [3403, 3416], [8138, 8151], [8213, 8226]], "Type": "Person", "Entity": "harri f . byrd"},{"Boundaries": [[8828, 8832]], "Type": "Person", "Entity": "wold"},{"Boundaries": [[7832, 7833], [8410, 8411]], "Type": "Person", "Entity": "w ."},{"Boundaries": [[6491, 6492], [7970, 7971]], "Type": "Person", "Entity": "b ."},{"Boundaries": [[8018, 8035], [8058, 8075]], "Type": "Person", "Entity": "winston l . prouti"},{"Boundaries": [[6302, 6316], [6339, 6353]], "Type": "Person", "Entity": "mike mansfield"},{"Boundaries": [[5449, 5450], [7199, 7200], [8825, 8826]], "Type": "Person", "Entity": "s ."},{"Boundaries": [[2899, 2914], [6891, 6906]], "Type": "Person", "Entity": "charl goodel"},{"Boundaries": [[7487, 7502], [7525, 7540]], "Type": "Person", "Entity": "john o . pastor"},{"Boundaries": [[3182, 3199], [4572, 4589]], "Type": "Person", "Entity": "lowel p . weicker"},{"Boundaries": [[8328, 8344], [8367, 8383]], "Type": "Person", "Entity": "henri m . jackson"},{"Boundaries": [[8715, 8723]], "Type": "Person", "Entity": "erickson"},{"Boundaries": [[7330, 7340]], "Type": "Person", "Entity": "metzenbaum"},{"Boundaries": [[6379, 6380], [8712, 8713]], "Type": "Person", "Entity": "e ."},{"Boundaries": [[4652, 4653], [6259, 6260], [6606, 6607], [7936, 7937]], "Type": "Person", "Entity": "j ."},{"Boundaries": [[7038, 7046]], "Type": "Person", "Entity": "otting"},{"Boundaries": [[2710, 2723], [4295, 4308]], "Type": "Person", "Entity": "georg murphi"},{"Boundaries": [[4187, 4198], [4221, 4232]], "Type": "Person", "Entity": "paul fannin"},{"Boundaries": [[6530, 6543], [6566, 6579]], "Type": "Person", "Entity": "howard cannon"},{"Boundaries": [[3338, 3348], [7661, 7671]], "Type": "Person", "Entity": "bill brock"},{"Boundaries": [[4655, 4659]], "Type": "Person", "Entity": "dodd"},{"Boundaries": [[5635, 5646], [5669, 5680]], "Type": "Person", "Entity": "ted kennedi"},{"Boundaries": [[7564, 7574]], "Type": "Person", "Entity": "mclaughlin"},{"Boundaries": [[2410, 2414]], "Type": "Person", "Entity": "roth"},{"Boundaries": [[4952, 4962], [4985, 4995]], "Type": "Person", "Entity": "hiram fong"},{"Boundaries": [[3261, 3277], [5546, 5562]], "Type": "Person", "Entity": "john glenn beall"},{"Boundaries": [[5593, 5600]], "Type": "Person", "Entity": "tyde"},{"Boundaries": [[4152, 4153]], "Type": "Person", "Entity": "p ."},{"Boundaries": [[3749, 3754]], "Type": "Person", "Entity": "nixon"},{"Boundaries": [[3222, 3236], [5488, 5502]], "Type": "Person", "Entity": "joseph tyde"},{"Boundaries": [[6647, 6667], [6690, 6710]], "Type": "Person", "Entity": "harrison a . william"},{"Boundaries": [[2530, 2541]], "Type": "Person", "Entity": "robert taft"},{"Boundaries": [[7829, 7830], [8101, 8102], [8593, 8594]], "Type": "Person", "Entity": "h ."},{"Boundaries": [[8633, 8649], [8672, 8688]], "Type": "Person", "Entity": "william proxmir"},{"Boundaries": [[2481, 2497], [7234, 7250]], "Type": "Person", "Entity": "stephen m . young"},{"Boundaries": [[2615, 2631], [7729, 7745]], "Type": "Person", "Entity": "ralph yarborough"},{"Boundaries": [[2799, 2816], [5073, 5090]], "Type": "Person", "Entity": "ralph tyler smith"},{"Boundaries": [[4035, 4046], [4114, 4125]], "Type": "Person", "Entity": "ted steven"},{"Boundaries": [[2987, 2993], [7285, 7291]], "Type": "Person", "Entity": "robert"},{"Boundaries": [[2238, 2253], [5906, 5921]], "Type": "Person", "Entity": "hubert humphrey"},{"Boundaries": [[6189, 6197]], "Type": "Person", "Entity": "danforth"},{"Boundaries": [[7202, 7208]], "Type": "Person", "Entity": "klepp"},{"Boundaries": [[6419, 6431], [6454, 6466]], "Type": "Person", "Entity": "roman hruska"},{"Boundaries": [[2147, 2162], [5856, 5871]], "Type": "Person", "Entity": "eugen mccarthi"},{"Boundaries": [[4463, 4464], [4915, 4916]], "Type": "Person", "Entity": "c ."},{"Boundaries": [[6776, 6790], [6813, 6827]], "Type": "Person", "Entity": "joseph montoya"},{"Boundaries": [[2994, 3001]], "Type": "Person", "Entity": "kennedi"},{"Boundaries": [[3605, 3609]], "Type": "Person", "Entity": "byrd"},{"Boundaries": [[5020, 5026]], "Type": "Person", "Entity": "heftel"},{"Boundaries": [[2339, 2351]], "Type": "Person", "Entity": "william roth"},{"Boundaries": [[3077, 3091], [4514, 4528]], "Type": "Person", "Entity": "thoma j . dodd"},{"Boundaries": [[7114, 7132], [7155, 7173]], "Type": "Person", "Entity": "quentin n . burdick"},{"Boundaries": [[2841, 2860], [5179, 5198]], "Type": "Person", "Entity": "adlai stevenson iii"},{"Boundaries": [[7939, 7945]], "Type": "Person", "Entity": "burton"},{"Boundaries": [[4424, 4430]], "Type": "Person", "Entity": "scheer"},{"Boundaries": [[7865, 7875], [7898, 7908]], "Type": "Person", "Entity": "frank moss"},{"Boundaries": [[6739, 6744]], "Type": "Person", "Entity": "gross"},{"Boundaries": [[6110, 6126], [6149, 6165]], "Type": "Person", "Entity": "stuart symington"},{"Boundaries": [[5819, 5825]], "Type": "Person", "Entity": "romney"},{"Boundaries": [[4620, 4626]], "Type": "Person", "Entity": "duffey"},{"Boundaries": [[7835, 7839]], "Type": "Person", "Entity": "bush"},{"Boundaries": [[7374, 7384], [7407, 7417]], "Type": "Person", "Entity": "hugh scott"},{"Boundaries": [[8752, 8765], [8788, 8801]], "Type": "Person", "Entity": "gale w . mcgee"},{"Boundaries": [[5946, 5955]], "Type": "Person", "Entity": "macgregor"},{"Boundaries": [[4918, 4924]], "Type": "Person", "Entity": "cramer"},{"Boundaries": [[5988, 6003], [6026, 6041]], "Type": "Person", "Entity": "john c . stenni"},{"Boundaries": [[5706, 5707], [7292, 7293]], "Type": "Person", "Entity": "a ."},{"Boundaries": [[8523, 8534], [8557, 8568]], "Type": "Person", "Entity": "robert byrd"},{"Boundaries": [[8104, 8108]], "Type": "Person", "Entity": "hoff"},{"Boundaries": [[4155, 4158]], "Type": "Person", "Entity": "kay"},{"Boundaries": [[6494, 6502]], "Type": "Person", "Entity": "morrison"},{"Boundaries": [[5263, 5275], [5298, 5310]], "Type": "Person", "Entity": "vanc hartk"},{"Boundaries": [[5337, 5338]], "Type": "Person", "Entity": "l ."},{"Boundaries": [[4741, 4756]], "Type": "Person", "Entity": "william v . roth"},{"Boundaries": [[7295, 7299]], "Type": "Person", "Entity": "taft"},{"Boundaries": [[8258, 8266]], "Type": "Person", "Entity": "rawl"},{}]