[{"Boundaries": [[3904, 3913]], "Type": "Person\r", "Entity": "ami grant"}, {"Boundaries": [[5243, 5254]], "Type": "Person\r", "Entity": "rod stewart"}, {"Boundaries": [[4386, 4399], [4788, 4801]], "Type": "Person\r", "Entity": "marshal hall"}, {"Boundaries": [[1657, 1668], [3863, 3874]], "Type": "Person\r", "Entity": "sandi patti"}, {"Boundaries": [[3825, 3835], [4289, 4299], [4432, 4442], [4589, 4599], [4654, 4664]], "Type": "Person\r", "Entity": "mark lowri"}, {"Boundaries": [[1804, 1818], [8548, 8562], [9251, 9265], [9577, 9591]], "Type": "Person\r", "Entity": "gloria gaither"}, {"Boundaries": [[5214, 5224]], "Type": "Person\r", "Entity": "elton john"}, {"Boundaries": [[3915, 3930], [4245, 4260], [4666, 4681]], "Type": "Person\r", "Entity": "michael english"}, {"Boundaries": [[4349, 4359], [4417, 4427], [4540, 4550], [4773, 4783]], "Type": "Person\r", "Entity": "guy penrod"}, {"Boundaries": [[1172, 1184]], "Type": "Person\r", "Entity": "hovi lister"}, {"Boundaries": [[3889, 3902]], "Type": "Person\r", "Entity": "don francisco"}, {"Boundaries": [[3837, 3853]], "Type": "Person\r", "Entity": "michael w . smith"}, {"Boundaries": [[1649, 1655], [3855, 3861]], "Type": "Person\r", "Entity": "carman"}, {"Boundaries": [[1787, 1800]], "Type": "Person\r", "Entity": "elvi presley"}, {"Boundaries": [[3967, 3982]], "Type": "Person\r", "Entity": "cynthia clawson"}, {"Boundaries": [[4361, 4373], [4686, 4698]], "Type": "Person\r", "Entity": "david phelp"}, {"Boundaries": [[209, 215], [831, 837], [1288, 1294], [2293, 2299], [5385, 5391]], "Type": "Person\r", "Entity": "gloria"}, {"Boundaries": [[1158, 1167]], "Type": "Person\r", "Entity": "jake hess"}, {"Boundaries": [[4228, 4243]], "Type": "Person\r", "Entity": "larnel harri"}, {"Boundaries": [[667, 680], [2219, 2232], [9498, 9511]], "Type": "Person\r", "Entity": "danni gaither"}, {"Boundaries": [[3932, 3947], [4332, 4347]], "Type": "Person\r", "Entity": "jonathan pierc"}, {"Boundaries": [[4375, 4384], [5282, 5291]], "Type": "Person\r", "Entity": "russ taff"}, {"Boundaries": [[1670, 1683], [6527, 6541], [6624, 6638], [7552, 7566]], "Type": "Organisation\r", "Entity": "the cathedr"}, {"Boundaries": [[3251, 3260], [9194, 9203], [9282, 9291]], "Type": "Organisation\r", "Entity": "zondervan"}, {"Boundaries": [[1629, 1647]], "Type": "Organisation\r", "Entity": "david crowder band"}, {"Boundaries": [[8313, 8337]], "Type": "Organisation\r", "Entity": "gospel music associ"}, {"Boundaries": [[8662, 8689]], "Type": "Organisation\r", "Entity": "indiana wesleyan univers"}, {"Boundaries": [[5226, 5239]], "Type": "Organisation\r", "Entity": "fleetwood mac"}, {"Boundaries": [[3479, 3502]], "Type": "Organisation\r", "Entity": "spring hill music group"}, {"Boundaries": [[1748, 1768]], "Type": "Organisation\r", "Entity": "the statler brother"}, {"Boundaries": [[291, 309], [4104, 4122], [4467, 4485], [5755, 5773], [6028, 6046], [6706, 6724], [6875, 6893], [6951, 6969], [7117, 7135], [7224, 7242], [7301, 7319], [7379, 7397], [7470, 7488], [7726, 7744], [7804, 7822], [7883, 7901], [7960, 7978], [8034, 8052], [8194, 8212], [8275, 8293], [10791, 10809]], "Type": "Organisation\r", "Entity": "gaither vocal band"}, {"Boundaries": [[1208, 1214], [1697, 1703]], "Type": "Organisation\r", "Entity": "speer"}, {"Boundaries": [[3268, 3282]], "Type": "Organisation\r", "Entity": "benson record"}, {"Boundaries": [[1220, 1229]], "Type": "Organisation\r", "Entity": "statesmen"}, {"Boundaries": [[3395, 3421]], "Type": "PopulatedPlace\r", "Entity": "brentwood , tennesse"}, {"Boundaries": [[508, 527], [5406, 5425]], "Type": "PopulatedPlace\r", "Entity": "alexandria , indiana"}]