[{"Boundaries": [[6391, 6397]], "Type": "Person", "Entity": "wilson"},{"Boundaries": [[22147, 22158]], "Type": "Person", "Entity": "kim beazley"},{"Boundaries": [[5996, 6012]], "Type": "Person", "Entity": "alexand wilson"},{"Boundaries": [[3066, 3081]], "Type": "Person", "Entity": "jame scullin"},{"Boundaries": [[10744, 10769]], "Type": "Person", "Entity": "general dougla macarthur"},{"Boundaries": [[6127, 6133], [6174, 6182], [17278, 17284], [17609, 17617]], "Type": "Person", "Entity": "fadden"},{"Boundaries": [[750, 761], [3737, 3748], [19963, 19974]], "Type": "Person", "Entity": "frank ford"},{"Boundaries": [[5979, 5991]], "Type": "Person", "Entity": "arthur cole"},{"Boundaries": [[6381, 6386]], "Type": "Person", "Entity": "cole"},{"Boundaries": [[6241, 6252]], "Type": "Person", "Entity": "lord gowri"},{"Boundaries": [[5724, 5737]], "Type": "Person", "Entity": "arthur fadden"},{"Boundaries": [[5, 11]], "Type": "Person", "Entity": "joseph"},{"Boundaries": [[0, 4]], "Type": "Person", "Entity": "john"},{"Boundaries": [[3940, 3945], [4021, 4026]], "Type": "Person", "Entity": "ford"},{"Boundaries": [[226, 236], [2589, 2599], [3408, 3418], [3840, 3850], [5619, 5629], [6207, 6217], [6554, 6564], [8394, 8404], [9612, 9622], [10027, 10037], [10213, 10223], [10388, 10400], [11065, 11075], [11089, 11099], [13013, 13023], [13092, 13102], [16423, 16433], [17130, 17140], [17831, 17841], [18301, 18311], [20576, 20586], [21649, 21661], [21759, 21770]], "Type": "Person", "Entity": "govern"},{"Boundaries": [[22133, 22142]], "Type": "Person", "Entity": "bob hawk"},{"Boundaries": [[7411, 7428]], "Type": "Person", "Entity": "winston churchil"},{"Boundaries": [[5411, 5423]], "Type": "Person", "Entity": "billi hugh"},{"Boundaries": [[23449, 23464]], "Type": "Person", "Entity": "terenc donovan"},{"Boundaries": [[2022, 2033]], "Type": "Person", "Entity": "ted needham"},{"Boundaries": [[6224, 6240], [12318, 12334]], "Type": "Person", "Entity": "governor - general"},{"Boundaries": [[23272, 23284]], "Type": "Person", "Entity": "geoff gallop"},{"Boundaries": [[1985, 1992]], "Type": "Person", "Entity": "needham"},{"Boundaries": [[774, 785], [20018, 20029]], "Type": "Person", "Entity": "ben chifley"},{"Boundaries": [[7397, 7406], [9683, 9692], [18903, 18912]], "Type": "Person", "Entity": "roosevelt"},{"Boundaries": [[12622, 12640]], "Type": "Person", "Entity": "menzi govern"},{"Boundaries": [[2843, 2857], [3176, 3190]], "Type": "Person", "Entity": "william watson"},{"Boundaries": [[21426, 21437], [22370, 22383], [22644, 22655], [22694, 22705], [22750, 22761], [22831, 22842]], "Type": "Person", "Entity": "john curtin"},{"Boundaries": [[4927, 4941]], "Type": "Person", "Entity": "robert menzi"},{"Boundaries": [[23588, 23603]], "Type": "Person", "Entity": "william mcinn"},{"Boundaries": [[3588, 3595], [3832, 3839]], "Type": "Person", "Entity": "scullin"},{"Boundaries": [[23371, 23388]], "Type": "Person", "Entity": "michael blakemor"},{"Boundaries": [[2859, 2865], [3500, 3506]], "Type": "Person", "Entity": "watson"},{"Boundaries": [[5032, 5039], [5202, 5209], [5780, 5788], [6107, 6114]], "Type": "Person", "Entity": "menzi"},{"Boundaries": [[12, 18], [246, 252], [432, 438], [684, 690], [814, 820], [915, 921], [961, 967], [1257, 1265], [1489, 1495], [2036, 2042], [2496, 2502], [2648, 2654], [2725, 2731], [2887, 2893], [3260, 3266], [3354, 3360], [3630, 3636], [3909, 3915], [3995, 4001], [4140, 4146], [4334, 4340], [4449, 4457], [4736, 4742], [5761, 5767], [6437, 6443], [6595, 6601], [6749, 6755], [7368, 7374], [7762, 7768], [7892, 7898], [9423, 9429], [10020, 10026], [10635, 10641], [10771, 10777], [11082, 11088], [11683, 11689], [12126, 12132], [12451, 12459], [12511, 12517], [12772, 12780], [12983, 12989], [13085, 13091], [17157, 17163], [17333, 17339], [17358, 17364], [17783, 17789], [18939, 18945], [19127, 19133], [19358, 19364], [19400, 19406], [19811, 19817], [20084, 20090], [20410, 20418], [20569, 20575], [21642, 21648], [22039, 22045], [22188, 22194], [22298, 22304], [22531, 22537], [22577, 22583], [22608, 22614], [22616, 22622], [22789, 22795], [22905, 22911], [23030, 23036], [23188, 23194], [23347, 23353], [23560, 23566]], "Type": "Person", "Entity": "curtin"},{"Boundaries": [[5452, 5458], [5631, 5637], [17289, 17295]], "Type": "Person", "Entity": "hugh"},{"Boundaries": [[10900, 10911], [10958, 10967], [11010, 11021], [19793, 19802]], "Type": "Person", "Entity": "macarthur"},{"Boundaries": [[9668, 9677], [11578, 11587], [18892, 18901]], "Type": "Person", "Entity": "churchil"},{"Boundaries": [[12495, 12509]], "Type": "Person", "Entity": "arthur calwel"},{"Boundaries": [[9294, 9301], [10476, 10482], [21772, 21778]], "Type": "Person", "Entity": "mark"},{}]