[{"Boundaries": [[749, 756], [799, 806], [1215, 1222], [1336, 1343], [2530, 2539], [2876, 2883]], "Type": "Person", "Entity": "campion"},{"Boundaries": [[40, 57]], "Type": "Person", "Entity": "margeri allingham"},{"Boundaries": [[2859, 2872]], "Type": "Person", "Entity": "peter davison"},{"Boundaries": [[283, 297], [398, 412]], "Type": "Person", "Entity": "albert campion"},{"Boundaries": [[2888, 2900]], "Type": "Person", "Entity": "brian glover"},{"Boundaries": [[344, 362]], "Type": "Person", "Entity": "magersfontein lugg"},{"Boundaries": [[2904, 2908]], "Type": "Person", "Entity": "lugg"},{}]