[{"Boundaries": [[2768, 2780]], "Type": "Person", "Entity": "famili seat"},{"Boundaries": [[2259, 2271]], "Type": "Person", "Entity": "walter scott"},{"Boundaries": [[5480, 5513]], "Type": "Person", "Entity": "walter john montagu dougla scott"},{"Boundaries": [[129, 149]], "Type": "Person", "Entity": "the duke of monmouth"},{"Boundaries": [[5767, 5788]], "Type": "Person", "Entity": "f . scott fitzgerald"},{"Boundaries": [[522, 527], [529, 542], [560, 565], [570, 575], [1161, 1166], [1196, 1201], [1397, 1402], [1788, 1793], [2098, 2103], [2846, 2851], [3665, 3670], [3712, 3717], [3757, 3762], [3827, 3832], [3874, 3879], [3924, 3929], [3959, 3964], [3993, 3998], [4009, 4014], [4070, 4075], [4086, 4091], [4186, 4191], [4234, 4239], [4281, 4286], [4332, 4337], [4468, 4473], [4646, 4651], [4699, 4704], [4747, 4752], [4879, 4884], [5005, 5010], [5205, 5210]], "Type": "Person", "Entity": "scott"},{"Boundaries": [[5086, 5114]], "Type": "Person", "Entity": "walter montagu dougla scott"},{"Boundaries": [[2768, 2780]], "Type": "Person", "Entity": "famili seat"},{"Boundaries": [[5279, 5305], [5383, 5409]], "Type": "Person", "Entity": "john montagu dougla scott"},{"Boundaries": [[5181, 5188]], "Type": "Person", "Entity": "charl"},{"Boundaries": [[190, 212]], "Type": "Person", "Entity": "charl ii of scotland"},{"Boundaries": [[256, 266]], "Type": "Person", "Entity": "ann scott"},{"Boundaries": [[5621, 5662]], "Type": "Person", "Entity": "walter john franci montagu dougla scott"},{"Boundaries": [[2334, 2340], [3058, 3064], [3102, 3108], [5711, 5717], [5816, 5822]], "Type": "Person", "Entity": "famili"},{"Boundaries": [[2467, 2480]], "Type": "Person", "Entity": "richard scott"},{}]