[{"Boundaries": [[4969, 4982], [5240, 5253], [5629, 5642]], "Type": "Person", "Entity": "leonard woolf"},{"Boundaries": [[705, 713], [1294, 1302], [2568, 2578]], "Type": "Person", "Entity": "virginia"},{"Boundaries": [[115, 129], [1312, 1326], [1351, 1365], [5601, 5615]], "Type": "Person", "Entity": "virginia woolf"},{"Boundaries": [[714, 723], [1303, 1310]], "Type": "Person", "Entity": "stephen"},{"Boundaries": [[5427, 5443]], "Type": "Person", "Entity": "arthur c . clark"},{"Boundaries": [[0, 7], [1339, 1346], [2587, 2596], [2825, 2832]], "Type": "Person", "Entity": "leonard"},{"Boundaries": [[2869, 2884]], "Type": "Person", "Entity": "trekki parson"},{"Boundaries": [[5738, 5758]], "Type": "Person", "Entity": "christoph ondaatj"},{"Boundaries": [[5486, 5506]], "Type": "Person", "Entity": "michael cunningham"},{"Boundaries": [[5584, 5597]], "Type": "Person", "Entity": "nicol kidman"},{"Boundaries": [[627, 642]], "Type": "Person", "Entity": "lytton strachey"},{"Boundaries": [[690, 703]], "Type": "Person", "Entity": "thobi stephen"},{"Boundaries": [[678, 688]], "Type": "Person", "Entity": "em forster"},{"Boundaries": [[15, 20], [143, 148], [218, 223], [241, 246], [361, 366], [794, 799], [918, 923], [1165, 1170], [1479, 1484], [1593, 1598], [1868, 1873], [2222, 2227], [2322, 2328], [2678, 2683], [2895, 2900], [3352, 3357], [3486, 3491], [3839, 3844], [3872, 3877], [4091, 4098], [5156, 5161], [5346, 5353], [5459, 5464], [5698, 5703]], "Type": "Person", "Entity": "woolf"},{"Boundaries": [[665, 673]], "Type": "Person", "Entity": "ge moor"},{"Boundaries": [[5839, 5855]], "Type": "Person", "Entity": "michael ondaatj"},{"Boundaries": [[644, 663]], "Type": "Person", "Entity": "john maynard keyn"},{"Boundaries": [[5657, 5672]], "Type": "Person", "Entity": "stephen dillan"},{}]