[{"Boundaries": [[1628, 1640], [1903, 1917]], "Type": "Person", "Entity": "pope zachari"},{"Boundaries": [[3133, 3135]], "Type": "Person", "Entity": "ix"},{"Boundaries": [[1605, 1613], [1705, 1713], [2560, 2568], [2823, 2831]], "Type": "Person", "Entity": "bonifac"},{"Boundaries": [[1344, 1358]], "Type": "Person", "Entity": "saint bonifac"},{"Boundaries": [[919, 932]], "Type": "Person", "Entity": "childer iii"},{"Boundaries": [[3125, 3132]], "Type": "Person", "Entity": "gregori"},{"Boundaries": [[0, 9], [1539, 1548], [1684, 1693], [1722, 1731], [2263, 2272], [2441, 2450], [2593, 2602], [2833, 2842]], "Type": "Person", "Entity": "vergilius"},{}]