[{"Boundaries": [[13133, 13136]], "Type": "Person", "Entity": "sun"},{"Boundaries": [[13287, 13303]], "Type": "Person", "Entity": "steven spielberg"},{"Boundaries": [[10764, 10778]], "Type": "Person", "Entity": "victor sassoon"},{"Boundaries": [[3823, 3834], [6213, 6224]], "Type": "Person", "Entity": "sun yat - sen"},{"Boundaries": [[879, 886], [10681, 10688], [10878, 10887], [11104, 11113]], "Type": "Person", "Entity": "sassoon"},{"Boundaries": [[13354, 13369]], "Type": "Person", "Entity": "neal stephenson"},{}]