[{"Boundaries": [[3617, 3640]], "Type": "Person\r", "Entity": "jame johnston keswick"}, {"Boundaries": [[4231, 4276]], "Type": "Organisation\r", "Entity": "the hongkong and shanghai bank corpor"}, {"Boundaries": [[4157, 4181]], "Type": "Organisation\r", "Entity": "bank of china ( hong kong )"}, {"Boundaries": [[4369, 4383]], "Type": "Organisation\r", "Entity": "hang seng bank"}, {"Boundaries": [[4434, 4448]], "Type": "Organisation\r", "Entity": "cathay pacif"}, {"Boundaries": [[4347, 4364]], "Type": "Organisation\r", "Entity": "bank of east asia"}, {"Boundaries": [[3960, 3964], [4294, 4298], [4327, 4331]], "Type": "Organisation\r", "Entity": "hsbc"}, {"Boundaries": [[1079, 1082]], "Type": "Organisation\r", "Entity": "mtr"}, {"Boundaries": [[4210, 4223]], "Type": "Organisation\r", "Entity": "bank of china"}, {"Boundaries": [[72, 100]], "Type": "PopulatedPlace\r", "Entity": "central and western district"}, {"Boundaries": [[124, 140], [1568, 1584], [2426, 2442], [9259, 9275]], "Type": "PopulatedPlace\r", "Entity": "hong kong island"}, {"Boundaries": [[44, 53], [350, 359], [3076, 3085], [3151, 3160], [3477, 3486], [3660, 3669], [3899, 3908], [3965, 3974], [4549, 4558], [4920, 4929], [4983, 4992], [5304, 5313], [6092, 6101], [6129, 6138], [6576, 6585], [6695, 6704], [7070, 7079], [7391, 7400], [7448, 7457], [7522, 7531], [7947, 7956], [8159, 8168], [8462, 8471], [9164, 9173], [9197, 9206], [9400, 9409]], "Type": "PopulatedPlace\r", "Entity": "hong kong"}]