[{"Boundaries": [[11, 16], [247, 252], [590, 595], [1312, 1317], [1920, 1925], [2506, 2511], [2524, 2529], [2807, 2812], [3096, 3101], [3136, 3141], [3522, 3527], [3793, 3800], [3969, 3974], [4011, 4016], [4126, 4131], [4264, 4269], [5052, 5057]], "Type": "Person", "Entity": "segal"},{"Boundaries": [[4047, 4052]], "Type": "Person", "Entity": "jame"},{"Boundaries": [[3492, 3499], [3986, 3993]], "Type": "Person", "Entity": "shorter"},{"Boundaries": [[3731, 3736]], "Type": "Person", "Entity": "frank"},{"Boundaries": [[1528, 1535]], "Type": "Person", "Entity": "william"},{"Boundaries": [[3773, 3785]], "Type": "Person", "Entity": "ambi burfoot"},{"Boundaries": [[3338, 3347]], "Type": "Person", "Entity": "jim mckay"},{"Boundaries": [[0, 5]], "Type": "Person", "Entity": "erich"},{"Boundaries": [[3355, 3370]], "Type": "Person", "Entity": "frank shorter"},{"Boundaries": [[55, 58], [143, 146], [294, 297], [409, 412], [495, 498], [621, 624], [682, 685], [743, 746], [1353, 1356], [1436, 1439], [1592, 1595], [1622, 1625], [1785, 1788], [1955, 1958], [2045, 2048], [2246, 2249], [2294, 2297], [2410, 2413], [2444, 2447], [2612, 2615], [2723, 2726], [2948, 2951], [3217, 3220], [3334, 3337], [3853, 3856], [4112, 4115], [4184, 4187], [4204, 4207], [4354, 4357], [4694, 4697], [4981, 4984]], "Type": "Person", "Entity": "and"},{"Boundaries": [[2020, 2028], [4917, 4925]], "Type": "Person", "Entity": "oliv"},{}]