[{"Boundaries": [[3813, 3827]], "Type": "Person", "Entity": "johann vesl"},{"Boundaries": [[2428, 2436]], "Type": "Person", "Entity": "linnaeus"},{"Boundaries": [[1903, 1918]], "Type": "Person", "Entity": "carolus clusius"},{"Boundaries": [[48, 56]], "Type": "Person", "Entity": "prospero"},{"Boundaries": [[1217, 1229]], "Type": "Person", "Entity": "andrea doria"},{"Boundaries": [[1989, 1995]], "Type": "Person", "Entity": "johann"},{"Boundaries": [[1382, 1388], [1851, 1859], [2490, 2496], [2676, 2682], [3143, 3149], [3656, 3662], [3789, 3795]], "Type": "Person", "Entity": "alpini"},{"Boundaries": [[1932, 1945]], "Type": "Person", "Entity": "johann bauhin"},{"Boundaries": [[0, 15], [2049, 2066], [4041, 4056]], "Type": "Person", "Entity": "prospero alpini"},{"Boundaries": [[1966, 1972]], "Type": "Person", "Entity": "bauhin"},{}]