[{"Boundaries": [[1291, 1295]], "Type": "Person", "Entity": "duff"},{"Boundaries": [[1296, 1300]], "Type": "Person", "Entity": "hill"},{"Boundaries": [[652, 658], [686, 692], [748, 754]], "Type": "Person", "Entity": "brown"},{"Boundaries": [[3291, 3313]], "Type": "Person", "Entity": "john bernard arbuthnot"},{"Boundaries": [[3585, 3591], [3657, 3663], [3732, 3738]], "Type": "Person", "Entity": "georg"},{"Boundaries": [[463, 467], [681, 685], [743, 747], [3788, 3792], [4605, 4609]], "Type": "Person", "Entity": "john"},{"Boundaries": [[3126, 3133]], "Type": "Person", "Entity": "osborn"},{"Boundaries": [[2945, 2959]], "Type": "Person", "Entity": "walter raleigh"},{"Boundaries": [[153, 158], [214, 219], [536, 541], [840, 846], [918, 923], [1053, 1059], [1067, 1072], [1098, 1103], [1128, 1133], [1532, 1537], [2270, 2277], [2496, 2501], [2683, 2688], [2864, 2870], [3046, 3051], [4251, 4256], [4265, 4270], [4294, 4299], [4429, 4434], [4653, 4658]], "Type": "Person", "Entity": "blake"},{"Boundaries": [[3433, 3446]], "Type": "Person", "Entity": "winslow homer"},{"Boundaries": [[3215, 3235]], "Type": "Person", "Entity": "ralph bernal osborn"},{"Boundaries": [[2932, 2937]], "Type": "Person", "Entity": "hous"},{"Boundaries": [[0, 3], [1086, 1089], [2941, 2944]], "Type": "Person", "Entity": "sir"},{"Boundaries": [[1090, 1097]], "Type": "Person", "Entity": "richard"},{"Boundaries": [[3119, 3125]], "Type": "Person", "Entity": "bernal"},{"Boundaries": [[4, 22]], "Type": "Person", "Entity": "henri arthur blake"},{"Boundaries": [[637, 640]], "Type": "Person", "Entity": "may"},{}]