[{"Boundaries": [[922, 933], [3277, 3288]], "Type": "Person", "Entity": "sleepwalk"},{"Boundaries": [[906, 916]], "Type": "Person", "Entity": "spider - man"},{"Boundaries": [[1288, 1298]], "Type": "Person", "Entity": "psylock"},{"Boundaries": [[1003, 1009]], "Type": "Person", "Entity": "exodus"},{"Boundaries": [[192, 196]], "Type": "Person", "Entity": "toad"},{"Boundaries": [[796, 802]], "Type": "Person", "Entity": "masqu"},{"Boundaries": [[4033, 4045], [4283, 4293]], "Type": "Person", "Entity": "dark beast"},{"Boundaries": [[648, 655]], "Type": "Person", "Entity": "cabl"},{"Boundaries": [[715, 721]], "Type": "Person", "Entity": "sauron"},{"Boundaries": [[1067, 1073], [1163, 1169]], "Type": "Person", "Entity": "pyro"},{"Boundaries": [[1556, 1565], [4397, 4406]], "Type": "Person", "Entity": "magneto"},{"Boundaries": [[680, 692], [3212, 3222]], "Type": "Person", "Entity": "cannonbal"},{"Boundaries": [[896, 904], [3804, 3812]], "Type": "Person", "Entity": "darkhawk"},{"Boundaries": [[819, 832]], "Type": "Person", "Entity": "shatterstar"},{"Boundaries": [[2, 11], [165, 174], [772, 781], [947, 956], [1248, 1257], [1334, 1343], [1488, 1497], [2046, 2055], [2170, 2179], [2416, 2425], [2671, 2680], [2820, 2829], [3351, 3360], [3679, 3690], [3848, 3857], [4367, 4376], [4420, 4429]], "Type": "Person", "Entity": "phantazia"},{"Boundaries": [[648, 655]], "Type": "Person", "Entity": "cabl"},{}]